oceandb/__init__.py
oceandb/api/__init__.py
oceandb/api/fastapi.py
oceandb/api/local.py
oceandb/api/models/Collection.py
oceandb/api/types.py
oceandb/app.py
oceandb/config.py
oceandb/db/__init__.py
oceandb/db/clickhouse.py
oceandb/db/duckdb.py
oceandb/db/index/__init__.py
oceandb/db/index/hnswlib.py
oceandb/errors.py
oceandb/server/__init__.py
oceandb/server/fastapi/__init__.py
oceandb/server/fastapi/types.py
oceandb/telemetry/__init__.py
oceandb/telemetry/events.py
oceandb/telemetry/posthog.py
oceandb/test/conftest.py
oceandb/test/property/invariants.py
oceandb/test/property/strategies.py
oceandb/test/property/test_add.py
oceandb/test/property/test_collections.py
oceandb/test/property/test_cross_version_persist.py
oceandb/test/property/test_embeddings.py
oceandb/test/property/test_filtering.py
oceandb/test/property/test_persist.py
oceandb/test/test_api.py
oceandb/test/test_chroma.py
oceandb/utils/ImageBind/.assets/bird_audio.wav
oceandb/utils/ImageBind/.assets/bird_image.jpg
oceandb/utils/ImageBind/.assets/car_audio.wav
oceandb/utils/ImageBind/.assets/car_image.jpg
oceandb/utils/ImageBind/.assets/dog_audio.wav
oceandb/utils/ImageBind/.assets/dog_image.jpg
oceandb/utils/ImageBind/.gitignore
oceandb/utils/ImageBind/CODE_OF_CONDUCT.md
oceandb/utils/ImageBind/CONTRIBUTING.md
oceandb/utils/ImageBind/LICENSE
oceandb/utils/ImageBind/README.md
oceandb/utils/ImageBind/bpe_simple_vocab_16e6.txt.gz
oceandb/utils/ImageBind/data.py
oceandb/utils/ImageBind/model_card.md
oceandb/utils/ImageBind/models/__init__.py
oceandb/utils/ImageBind/models/helpers.py
oceandb/utils/ImageBind/models/imagebind_model.py
oceandb/utils/ImageBind/models/multimodal_preprocessors.py
oceandb/utils/ImageBind/models/transformer.py
oceandb/utils/ImageBind/requirements.txt
oceandb/utils/__init__.py
oceandb/utils/embedding_functions.py
oceandb-0.1.0.dist-info/LICENSE
oceandb-0.1.0.dist-info/WHEEL
oceandb-0.1.0.dist-info/METADATA
oceandb-0.1.0.dist-info/RECORD
