Metadata-Version: 2.1
Name: oceandb
Version: 0.1.0
Summary: Ocean.
Author: Kye Gomez
Author-email: kye@apac.ai
Requires-Python: >=3.7,<4.0
Classifier: Programming Language :: Python :: 3
Classifier: Programming Language :: Python :: 3.7
Classifier: Programming Language :: Python :: 3.8
Classifier: Programming Language :: Python :: 3.9
Classifier: Programming Language :: Python :: 3.10
Classifier: Programming Language :: Python :: 3.11
Requires-Dist: clickhouse_connect (>=0.5.7,<0.6.0)
Requires-Dist: duckdb (>=0.7.1,<0.8.0)
Requires-Dist: fastapi (>=0.85.1,<0.86.0)
Requires-Dist: hnswlib (>=0.7,<0.8)
Requires-Dist: numpy (>=1.21.6,<2.0.0)
Requires-Dist: pandas (>=1.3,<2.0)
Requires-Dist: posthog (>=2.4.0,<3.0.0)
Requires-Dist: pydantic (>=1.9,<2.0)
Requires-Dist: requests (>=2.28,<3.0)
Requires-Dist: sentence-transformers (>=2.2.2,<3.0.0)
Requires-Dist: typing_extensions (>=4.5.0,<5.0.0)
Requires-Dist: uvicorn[standard] (>=0.18.3,<0.19.0)
Project-URL: Bug Tracker, https://github.com/kyegomez/ocean/issues
Project-URL: Homepage, https://github.com/kyegomez/ocean
